[
  {
    "title": "Evaluating Graph Vulnerability and Robustness using TIGER",
    "person" : [
      {
        "name": "Scott Freitas",
        "url": "https://google.ca"
      },
      {
        "name": "Duen Horng (Polo) Chau",
        "url": "https://google.ca"
      }
    ],
    "description": "https://google.ca",
    "project": "https://google.ca",
    "pdf": "https://google.ca",
    "demo": "https://google.ca",
    "video": "https://google.ca",
    "code": "https://google.ca",
    "bibtext": "https://google.ca",
    "other": "https://google.ca"
  },
  {
    "title": "Extracting Knowledge For Adversarial Detection and Defense in Deep Learning",
    "person" : [
      {
        "name": "Scott Freitas",
        "url": "https://google.ca"
      },
      {
        "name": "Duen Horng (Polo) Chau",
        "url": "https://google.ca"
      }
    ],
    "description": "https://google.ca",
    "project": "https://google.ca",
    "pdf": "https://google.ca",
    "demo": "https://google.ca",
    "video": "https://google.ca",
    "code": "https://google.ca",
    "bibtext": "https://google.ca",
    "other": "https://google.ca"
  },
  {
    "title": "X-Rank: Explainable Ranking in Complex Multi-Layered Networks",
    "person" : [
      {
        "name": "Scott Freitas",
        "url": "https://google.ca"
      },
      {
        "name": "Duen Horng (Polo) Chau",
        "url": "https://google.ca"
      }
    ],
    "description": "https://google.ca",
    "project": "https://google.ca",
    "pdf": "https://google.ca",
    "demo": "https://google.ca",
    "video": "https://google.ca",
    "code": "https://google.ca",
    "bibtext": "https://google.ca",
    "other": "https://google.ca"
  },
  {
    "title": "Rapid Analysis of Network Connectivity",
    "person" : [
      {
        "name": "Scott Freitas",
        "url": "https://google.ca"
      },
      {
        "name": "Duen Horng (Polo) Chau",
        "url": "https://google.ca"
      }
    ],
    "description": "https://google.ca",
    "project": "https://google.ca",
    "pdf": "https://google.ca",
    "demo": "https://google.ca",
    "video": "https://google.ca",
    "code": "https://google.ca",
    "bibtext": "https://google.ca",
    "other": "https://google.ca"
  }
]
